casablanca_Stock/Action.py
casablanca_Stock/__init__.py
casablanca_bourse-0.2.0.dist-info/LICENSE
casablanca_bourse-0.2.0.dist-info/METADATA
casablanca_bourse-0.2.0.dist-info/WHEEL
casablanca_bourse-0.2.0.dist-info/top_level.txt
casablanca_bourse-0.2.0.dist-info/RECORD
