Metadata-Version: 2.1
Name: casablanca-bourse
Version: 0.2.0
License-File: LICENSE
Requires-Dist: requests
Requires-Dist: beautifulsoup4
Requires-Dist: pandas
